gomoku/__init__.py
gomoku/__main__.py
gomoku/ai.py
gomoku/board.py
gomoku/game.py
gomoku/ui.py
gomoku_terminal-1.0.1.dist-info/LICENSE
gomoku_terminal-1.0.1.dist-info/METADATA
gomoku_terminal-1.0.1.dist-info/WHEEL
gomoku_terminal-1.0.1.dist-info/entry_points.txt
gomoku_terminal-1.0.1.dist-info/top_level.txt
gomoku_terminal-1.0.1.dist-info/RECORD
