Metadata-Version: 2.1
Name: gomoku-terminal
Version: 1.0.1
Summary: A terminal-based Gomoku (Five in a Row) game with AI opponents and keyboard control
Author-email: Your Name <your.email@example.com>
Project-URL: Homepage, https://github.com/yourusername/gomoku-terminal
Project-URL: Repository, https://github.com/yourusername/gomoku-terminal
Project-URL: Issues, https://github.com/yourusername/gomoku-terminal/issues
Keywords: game,gomoku,terminal,ai,curses
Classifier: Development Status :: 4 - Beta
Classifier: Intended Audience :: End Users/Desktop
Classifier: Topic :: Games/Entertainment :: Board Games
Classifier: License :: OSI Approved :: MIT License
Classifier: Programming Language :: Python :: 3
Classifier: Programming Language :: Python :: 3.8
Classifier: Programming Language :: Python :: 3.9
Classifier: Programming Language :: Python :: 3.10
Classifier: Programming Language :: Python :: 3.11
Classifier: Programming Language :: Python :: 3.12
Classifier: Operating System :: OS Independent
Classifier: Environment :: Console :: Curses
Requires-Python: >=3.8
License-File: LICENSE
Requires-Dist: windows-curses>=2.3.0; platform_system == "Windows"
